CHANGELOG.md
eth_2_key_manager_api_client/__init__.py
eth_2_key_manager_api_client/api/__init__.py
eth_2_key_manager_api_client/api/fee_recipient.py
eth_2_key_manager_api_client/api/gas_limit.py
eth_2_key_manager_api_client/api/local_key_manager.py
eth_2_key_manager_api_client/api/remote_key_manager.py
eth_2_key_manager_api_client/client.py
eth_2_key_manager_api_client/errors.py
eth_2_key_manager_api_client/eth_2_keymanager.py
eth_2_key_manager_api_client/helpers.py
eth_2_key_manager_api_client/models/__init__.py
eth_2_key_manager_api_client/models/delete_keys_json_body.py
eth_2_key_manager_api_client/models/delete_keys_response.py
eth_2_key_manager_api_client/models/delete_keys_response_data_item.py
eth_2_key_manager_api_client/models/delete_keys_response_data_item_status.py
eth_2_key_manager_api_client/models/delete_remote_keys_json_body.py
eth_2_key_manager_api_client/models/delete_remote_keys_response.py
eth_2_key_manager_api_client/models/delete_remote_keys_response_data_item.py
eth_2_key_manager_api_client/models/delete_remote_keys_response_data_item_status.py
eth_2_key_manager_api_client/models/error_response.py
eth_2_key_manager_api_client/models/fee_recipient.py
eth_2_key_manager_api_client/models/gas_limit.py
eth_2_key_manager_api_client/models/import_keystores_json_body.py
eth_2_key_manager_api_client/models/import_keystores_response.py
eth_2_key_manager_api_client/models/import_keystores_response_data_item.py
eth_2_key_manager_api_client/models/import_keystores_response_data_item_status.py
eth_2_key_manager_api_client/models/import_remote_keys_json_body.py
eth_2_key_manager_api_client/models/import_remote_keys_json_body_remote_keys_item.py
eth_2_key_manager_api_client/models/import_remote_keys_response.py
eth_2_key_manager_api_client/models/import_remote_keys_response_data_item.py
eth_2_key_manager_api_client/models/import_remote_keys_response_data_item_status.py
eth_2_key_manager_api_client/models/import_remote_signer_definition.py
eth_2_key_manager_api_client-0.3.0.dist-info/LICENSE
eth_2_key_manager_api_client-0.3.0.dist-info/METADATA
eth_2_key_manager_api_client-0.3.0.dist-info/WHEEL
eth_2_key_manager_api_client-0.3.0.dist-info/RECORD
