Metadata-Version: 2.1
Name: eth-2-key-manager-api-client
Version: 0.3.0
Summary: A client library for accessing ETH2 key manager API
Author: Karol Piwowarski
Author-email: karol@slingnode.com
Requires-Python: >=3.9,<4.0
Classifier: Programming Language :: Python :: 3
Classifier: Programming Language :: Python :: 3.9
Classifier: Programming Language :: Python :: 3.10
Classifier: Programming Language :: Python :: 3.11
Classifier: Programming Language :: Python :: 3.12
Requires-Dist: attrs (==23.1.0)
Requires-Dist: exceptiongroup (>=1.2.0,<2.0.0) ; python_version == "3.9.*" or python_version == "3.10.*"
Requires-Dist: httpx (>=0.25.0,<0.26.0)
